face_eevee/__init__.py
face_eevee/config.py
face_eevee/face_eevee.py
face_eevee/utils.py
face_eevee-0.1.1.dist-info/METADATA
face_eevee-0.1.1.dist-info/RECORD
face_eevee-0.1.1.dist-info/WHEEL
face_eevee-0.1.1.dist-info/entry_points.txt
face_eevee-0.1.1.dist-info/top_level.txt
