Metadata-Version: 2.1
Name: face-eevee
Version: 0.1.1
Summary: Early test of eos lib for the EEVEE plateform
Home-page: https://github.com/alexisfcote/face_eevee
Author: Alexis Fortin-Cote
Author-email: alexisfcote@gmail.com
License: MIT
Platform: UNKNOWN
Classifier: Development Status :: 2 - Pre-Alpha
Classifier: License :: OSI Approved :: MIT License
Classifier: Operating System :: Microsoft :: Windows
Classifier: Programming Language :: Python
Classifier: Programming Language :: Python :: 3
Classifier: Programming Language :: Python :: 3.5
Classifier: Programming Language :: Python :: 3.6
Classifier: Topic :: Scientific/Engineering :: Image Recognition
Requires-Dist: imutils
Requires-Dist: numpy
Requires-Dist: opencv-python
Requires-Dist: eos-py
Requires-Dist: dlib
Requires-Dist: matplotlib
